{
  "type": "FeatureCollection",
  "features": [
    {
      "type": "Feature",
      "properties": {
        "stroke": "#9ae5ff",
        "stroke-width": 2,
        "stroke-opacity": 1,
        "fill": "#555555",
        "fill-opacity": 0.5,
        "name": "九台市"
      },
      "geometry": {
        "type": "MultiPolygon",
        "coordinates": [
          [
            [
              [
                126.407345,
                44.523843
              ],
              [
                126.387198515625,
                44.5164443183594
              ],
              [
                126.342345,
                44.5200484443359
              ],
              [
                126.292345,
                44.5160305
              ],
              [
                126.215636015625,
                44.5221944404297
              ],
              [
                126.089766875,
                44.4947402167969
              ],
              [
                126.050343046875,
                44.4667891669922
              ],
              [
                125.9919153125,
                44.4491970039063
              ],
              [
                125.993150664063,
                44.4338430000001
              ],
              [
                125.991539335938,
                44.413843
              ],
              [
                125.993043242188,
                44.3951711250001
              ],
              [
                125.926363554688,
                44.4005287910156
              ],
              [
                125.91271609375,
                44.3964455390625
              ],
              [
                125.93271609375,
                44.3792147041016
              ],
              [
                125.95197390625,
                44.3557784248047
              ],
              [
                125.866417265625,
                44.3233119941407
              ],
              [
                125.85271609375,
                44.3392147041016
              ],
              [
                125.830631132813,
                44.3490706611329
              ],
              [
                125.81271609375,
                44.3892147041016
              ],
              [
                125.79056765625,
                44.3984712958985
              ],
              [
                125.77271609375,
                44.3584712958985
              ],
              [
                125.73197390625,
                44.3492147041016
              ],
              [
                125.708951445313,
                44.3363692451172
              ],
              [
                125.647916289063,
                44.317993390625
              ],
              [
                125.612965117188,
                44.3208016181641
              ],
              [
                125.580816679688,
                44.2694692207032
              ],
              [
                125.5965246875,
                44.2559334541016
              ],
              [
                125.587345,
                44.213843
              ],
              [
                125.5765246875,
                44.1697975898438
              ],
              [
                125.5846496875,
                44.1335732246094
              ],
              [
                125.577345,
                44.103843
              ],
              [
                125.584420195313,
                44.0946749091797
              ],
              [
                125.6486340625,
                44.1125557685547
              ],
              [
                125.66170046875,
                44.1294869208984
              ],
              [
                125.694522734375,
                44.1491158271484
              ],
              [
                125.691607695313,
                44.168843
              ],
              [
                125.693082304688,
                44.178843
              ],
              [
                125.691031523438,
                44.1927315498047
              ],
              [
                125.732345,
                44.186626203125
              ],
              [
                125.759854765625,
                44.1906917548829
              ],
              [
                125.763116484375,
                44.1686324287109
              ],
              [
                125.751534453125,
                44.1289168525391
              ],
              [
                125.76310671875,
                44.0789852119141
              ],
              [
                125.761607695313,
                44.068843
              ],
              [
                125.765513945313,
                44.0423879218751
              ],
              [
                125.749176054688,
                44.0152980781251
              ],
              [
                125.753082304688,
                43.988843
              ],
              [
                125.744351835938,
                43.929749982422
              ],
              [
                125.810582304688,
                43.9157741523437
              ],
              [
                125.813824492188,
                43.8938430000001
              ],
              [
                125.81156375,
                43.8785512519531
              ],
              [
                125.817345,
                43.863843
              ],
              [
                125.851846953125,
                43.8553688789063
              ],
              [
                125.877345,
                43.8610848212891
              ],
              [
                125.897345,
                43.856601178711
              ],
              [
                125.912623320313,
                43.8600264716797
              ],
              [
                125.952213164063,
                43.8433968330079
              ],
              [
                125.97326296875,
                43.8579274726563
              ],
              [
                125.98142703125,
                43.8697585273437
              ],
              [
                126.02326296875,
                43.8779274726563
              ],
              [
                126.037345,
                43.883843
              ],
              [
                126.029893828125,
                43.8988283515626
              ],
              [
                126.039185820313,
                43.9178523994141
              ],
              [
                126.019420195313,
                43.9278523994141
              ],
              [
                126.029722929688,
                43.9489455390625
              ],
              [
                126.017345,
                43.9738430000001
              ],
              [
                126.012896757813,
                43.9793959785156
              ],
              [
                125.992896757813,
                43.9954116035156
              ],
              [
                126.00873171875,
                44.0381056953126
              ],
              [
                126.032896757813,
                44.0482900214844
              ],
              [
                126.041793242188,
                44.0593959785156
              ],
              [
                126.052896757813,
                44.0682900214844
              ],
              [
                126.095553007813,
                44.1215535712891
              ],
              [
                126.133214140625,
                44.1168691230469
              ],
              [
                126.13166140625,
                44.129341046875
              ],
              [
                126.152896757813,
                44.1382900214844
              ],
              [
                126.170079375,
                44.1597463203126
              ],
              [
                126.199210234375,
                44.1561232734375
              ],
              [
                126.236920195313,
                44.1782900214844
              ],
              [
                126.262896757813,
                44.1693959785156
              ],
              [
                126.272423125,
                44.1575044990234
              ],
              [
                126.291954375,
                44.1896651435547
              ],
              [
                126.331793242188,
                44.1782900214844
              ],
              [
                126.437345,
                44.173843
              ],
              [
                126.465225859375,
                44.1809975410157
              ],
              [
                126.459757109375,
                44.2053908515625
              ],
              [
                126.49326296875,
                44.2179274726563
              ],
              [
                126.497345,
                44.2338430000001
              ],
              [
                126.452745390625,
                44.2423574042969
              ],
              [
                126.482672148438,
                44.2989083076172
              ],
              [
                126.472154570313,
                44.3086525703125
              ],
              [
                126.462535429688,
                44.3390334296875
              ],
              [
                126.444732695313,
                44.3555306220703
              ],
              [
                126.472535429688,
                44.3686525703125
              ],
              [
                126.482154570313,
                44.4001210761719
              ],
              [
                126.46134890625,
                44.4193978095704
              ],
              [
                126.421510039063,
                44.4178188300781
              ],
              [
                126.43263796875,
                44.438843
              ],
              [
                126.422154570313,
                44.4586525703125
              ],
              [
                126.412535429688,
                44.4801210761719
              ],
              [
                126.432740507813,
                44.498843
              ],
              [
                126.416964140625,
                44.5134615302735
              ],
              [
                126.407345,
                44.523843
              ]
            ]
          ]
        ]
      }
    }
  ]
}